wumpy/interactions/__init__.py
wumpy/interactions/_app.py
wumpy/interactions/_compat.py
wumpy/interactions/_errors.py
wumpy/interactions/_middleware.py
wumpy/interactions/_models.py
wumpy/interactions/_utils.py
wumpy/interactions/py.typed
wumpy/interactions/commands/__init__.py
wumpy/interactions/commands/_base.py
wumpy/interactions/commands/_checks.py
wumpy/interactions/commands/_context.py
wumpy/interactions/commands/_middleware.py
wumpy/interactions/commands/_option.py
wumpy/interactions/commands/_registrar.py
wumpy/interactions/commands/_slash.py
wumpy/interactions/components/__init__.py
wumpy/interactions/components/_handler.py
wumpy_interactions-0.1.0.dist-info/WHEEL
wumpy_interactions-0.1.0.dist-info/METADATA
wumpy_interactions-0.1.0.dist-info/RECORD
